{
  "name": "PyWeb Academy — Learn",
  "short_name": "PyWeb Learn",
  "description": "Învață Python, JavaScript, HTML și CSS interactiv. Lecții cu teorie + exerciții.",
  "start_url": "/learn/guest",
  "scope": "/learn",
  "display": "standalone",
  "orientation": "portrait-primary",
  "background_color": "#1e3a8a",
  "theme_color": "#1e3a8a",
  "categories": ["education", "productivity"],
  "lang": "ro",
  "icons": [
    {
      "src": "/icon-192.png",
      "sizes": "192x192",
      "type": "image/png",
      "purpose": "any"
    },
    {
      "src": "/icon-192.png",
      "sizes": "192x192",
      "type": "image/png",
      "purpose": "maskable"
    },
    {
      "src": "/icon-512.png",
      "sizes": "512x512",
      "type": "image/png",
      "purpose": "any"
    },
    {
      "src": "/icon-512.png",
      "sizes": "512x512",
      "type": "image/png",
      "purpose": "maskable"
    }
  ],
  "shortcuts": [
    {
      "name": "Modulele mele",
      "short_name": "Module",
      "description": "Vezi modulele tale",
      "url": "/learn"
    },
    {
      "name": "Login",
      "short_name": "Login",
      "url": "/learn/login"
    }
  ]
}
